{
    "id": "micro-commercial-components-1n4148wx-tp",
    "reference": "D",
    "mpn": "1N4148WX-TP",
    "category": "Semiconductor",
    "type": "Small Signal Diode, Single, 100 V, 300 mA, 1 V, 4 ns, 2 A",
    "datasheetUrl": "https://www.mccsemi.com/pdf/Products/1N4148WX(SOD323).pdf",
    "tags": [
        "SMT",
        "DIODE",
        "SEMICONDUCTOR",
        "RECTIFIER"
    ],
    "assets": {
        "blendfile": true,
        "symbol": false,
        "footprint": true
    },
    "symbolId": "1n4148wx-tp",
    "footprintId": "sod-323",
    "blendfileId": "sod-323",
    "manufacturerId": "micro-commercial-components",
    "tagIds": [
        "smt",
        "diode",
        "semiconductor",
        "rectifier"
    ]
}