{
    "reference":"L",
    "symbol":"L_2u2_0.6A_0805",
    "footprint":"L_0805_2012Metric",
    "datasheet":"https://product.tdk.com/system/files/dam/doc/product/inductor/inductor/smd/catalog/inductor_commercial_decoupling_mlz2012_en.pdf",
    "manufacturer":"TDK",
    "mpn":"MLZ2012M2R2HT000",
    "displayName":null,
    "description":"Multilayer Inductor, 2.2 \u00b5H, 0.208 ohm, 100 MHz, 600 mA, 0805 [2012 Metric], MLZ",
    "keywords":"SMT, INDUCTOR, PASSIVE",
    "gitHub":null,
    "blender_model":"L_0805_2012Metric",
    "gltf_model":"L_0805_2012Metric",
    "pads":[
        {
            "reference":"1",
            "pin_name":"~",
            "alternate_pin_names":[],
            "electrical_type":"passive"
        },
        {
            "reference":"2",
            "pin_name":"~",
            "alternate_pin_names":[],
            "electrical_type":"passive"
        }
    ]
}