{
    "reference":"Q",
    "symbol":"PJA3404",
    "footprint":"SOT-23-3",
    "datasheet":"https://www.mouser.com/datasheet/2/1057/PJA3404-1867365.pdf",
    "manufacturer":"PANJIT",
    "mpn":"PJA3404_R1_00001",
    "displayName":null,
    "description":"MOSFET, N Channel, 30V, 5.6A, 0.045 ohm, SOT-23, Surface Mount",
    "keywords":"SMT, TRANSISTOR, SEMICONDUCTOR, MOSFET",
    "gitHub":null,
    "blender_model":"SOT-23-3",
    "gltf_model":"SOT-23-3",
    "pads":[
        {
            "reference":"1",
            "pin_name":"G",
            "alternate_pin_names":[],
            "electrical_type":"input"
        },
        {
            "reference":"2",
            "pin_name":"S",
            "alternate_pin_names":[],
            "electrical_type":"passive"
        },
        {
            "reference":"3",
            "pin_name":"D",
            "alternate_pin_names":[],
            "electrical_type":"passive"
        }
    ]
}