{
    "id": "silicon-labs-si7021-a20-gm1r",
    "reference": "U",
    "mpn": "Si7021-A20-GM1R",
    "category": "IC",
    "type": "Humidity/Temperature Sensor, 0% to 100% RH/-40\u00b0C to 85\u00b0C Range, I2C, Digital, 1.9V to 3.6V, DFN-6",
    "datasheetUrl": "https://www.mouser.pl/datasheet/2/368/Si7021_A20-1397917.pdf",
    "tags": [
        "SENSOR",
        "I2C"
    ],
    "assets": {
        "blendfile": true,
        "symbol": true,
        "footprint": true
    },
    "symbolId": "si7021",
    "footprintId": "dfn-6-1ep-3x3mm-p1mm-ep1-5x2-4mm",
    "blendfileId": "dfn-6-1ep-3x3mm-p1mm-ep1-5x2-4mm",
    "manufacturerId": "silicon-labs",
    "tagIds": [
        "sensor",
        "i2c"
    ]
}