{
    "reference":"Q",
    "symbol":"IRLML2502TRPBF",
    "footprint":"SOT-23-3",
    "datasheet":"https://www.infineon.com/dgdl/Infineon-IRLML2502-DataSheet-v01_01-EN.pdf?fileId=5546d462533600a401535668048e2606",
    "manufacturer":"Infineon",
    "mpn":"IRLML2502TRPBF",
    "displayName":null,
    "description":"Power MOSFET, N Channel, 30 V, 5 A, 0.022 ohm, SOT-23, Surface Mount",
    "keywords":"SMT, TRANSISTOR, SEMICONDUCTOR, NMOS, MOSFET",
    "gitHub":null,
    "blender_model":"SOT-23-3-infineon-irlml2502trpbf",
    "gltf_model":"SOT-23-3-infineon-irlml2502trpbf",
    "pads":[
        {
            "reference":"1",
            "pin_name":"G",
            "alternate_pin_names":[],
            "electrical_type":"input"
        },
        {
            "reference":"2",
            "pin_name":"D",
            "alternate_pin_names":[],
            "electrical_type":"passive"
        },
        {
            "reference":"3",
            "pin_name":"S",
            "alternate_pin_names":[],
            "electrical_type":"passive"
        }
    ]
}