{
    "reference":"J",
    "symbol":"Molex_Nano-Fit_2x3_1053101206",
    "footprint":"Conn_Molex_Nano-Fit_2x3_1053101206",
    "datasheet":"https://www.molex.com/pdm_docs/sd/1053101206_sd.pdf",
    "manufacturer":"Molex",
    "mpn":"1053101206",
    "displayName":null,
    "description":"Pin Header, Vertical, Power, 2.5 mm, 2 Rows, 6 Contacts, Through Hole Straight, Nano-Fit 105310",
    "keywords":"CONNECTOR, THT, WIRE-BOARD",
    "gitHub":null,
    "blender_model":"Conn_Molex_Nano-Fit_2x3_1053101206",
    "gltf_model":null,
    "pads":[
        {
            "reference":"1",
            "pin_name":"~",
            "alternate_pin_names":[],
            "electrical_type":"passive"
        },
        {
            "reference":"2",
            "pin_name":"~",
            "alternate_pin_names":[],
            "electrical_type":"passive"
        },
        {
            "reference":"3",
            "pin_name":"~",
            "alternate_pin_names":[],
            "electrical_type":"passive"
        },
        {
            "reference":"4",
            "pin_name":"~",
            "alternate_pin_names":[],
            "electrical_type":"passive"
        },
        {
            "reference":"5",
            "pin_name":"~",
            "alternate_pin_names":[],
            "electrical_type":"passive"
        },
        {
            "reference":"6",
            "pin_name":"~",
            "alternate_pin_names":[],
            "electrical_type":"passive"
        }
    ]
}