{
    "id": "diodes-incorporated-pi3usb102gzlex",
    "reference": "U",
    "mpn": "PI3USB102GZLEX",
    "category": "IC",
    "type": "USB Switch IC 1 Channel 10-TQFN (1.3x1.6)",
    "datasheetUrl": "https://www.onsemi.com/pub/Collateral/FSUSB42-D.PDF",
    "tags": [
        "IC"
    ],
    "assets": {
        "blendfile": true,
        "symbol": true,
        "footprint": true
    },
    "symbolId": "pi3usb102gzlex",
    "footprintId": "uqfn-10-1-4x1-8x0-5mm-p0-4mm",
    "blendfileId": "uqfn-10-1-4x1-8x0-5mm-p0-4mm",
    "manufacturerId": "diodes-incorporated",
    "tagIds": [
        "ic"
    ]
}