{
    "reference":"J",
    "symbol":"DisplayPort_Molex_472720001",
    "footprint":"DisplayPort_Receptacle_Molex_472720001",
    "datasheet":"https://www.molex.com/en-us/products/part-detail/472720001",
    "manufacturer":"Molex",
    "mpn":"472720001",
    "displayName":null,
    "description":"DisplayPort Receptacle Connector 20 Position Surface Mount, Right Angle; Through Hole",
    "keywords":"DISPLAYPORT, CONNECTOR, SMT, THT, HORIZONTAL",
    "gitHub":null,
    "blender_model":"DisplayPort_Receptacle_Molex_472720001",
    "gltf_model":null,
    "pads":[
        {
            "reference":"1",
            "pin_name":"TXD0+",
            "alternate_pin_names":[],
            "electrical_type":"bidirectional"
        },
        {
            "reference":"2",
            "pin_name":"GND",
            "alternate_pin_names":[],
            "electrical_type":"passive"
        },
        {
            "reference":"3",
            "pin_name":"TXD0-",
            "alternate_pin_names":[],
            "electrical_type":"bidirectional"
        },
        {
            "reference":"4",
            "pin_name":"TXD1+",
            "alternate_pin_names":[],
            "electrical_type":"bidirectional"
        },
        {
            "reference":"5",
            "pin_name":"GND",
            "alternate_pin_names":[],
            "electrical_type":"passive"
        },
        {
            "reference":"6",
            "pin_name":"TXD1-",
            "alternate_pin_names":[],
            "electrical_type":"bidirectional"
        },
        {
            "reference":"7",
            "pin_name":"TXD2+",
            "alternate_pin_names":[],
            "electrical_type":"bidirectional"
        },
        {
            "reference":"8",
            "pin_name":"GND",
            "alternate_pin_names":[],
            "electrical_type":"passive"
        },
        {
            "reference":"9",
            "pin_name":"TXD2-",
            "alternate_pin_names":[],
            "electrical_type":"bidirectional"
        },
        {
            "reference":"10",
            "pin_name":"TXD3+",
            "alternate_pin_names":[],
            "electrical_type":"bidirectional"
        },
        {
            "reference":"11",
            "pin_name":"GND",
            "alternate_pin_names":[],
            "electrical_type":"power_in"
        },
        {
            "reference":"12",
            "pin_name":"TXD3-",
            "alternate_pin_names":[],
            "electrical_type":"bidirectional"
        },
        {
            "reference":"13",
            "pin_name":"CFG1",
            "alternate_pin_names":[],
            "electrical_type":"passive"
        },
        {
            "reference":"14",
            "pin_name":"CFG2",
            "alternate_pin_names":[],
            "electrical_type":"passive"
        },
        {
            "reference":"15",
            "pin_name":"AUX+",
            "alternate_pin_names":[],
            "electrical_type":"bidirectional"
        },
        {
            "reference":"16",
            "pin_name":"GND",
            "alternate_pin_names":[],
            "electrical_type":"passive"
        },
        {
            "reference":"17",
            "pin_name":"AUX-",
            "alternate_pin_names":[],
            "electrical_type":"bidirectional"
        },
        {
            "reference":"18",
            "pin_name":"HPD",
            "alternate_pin_names":[],
            "electrical_type":"passive"
        },
        {
            "reference":"19",
            "pin_name":"RTN",
            "alternate_pin_names":[],
            "electrical_type":"power_in"
        },
        {
            "reference":"20",
            "pin_name":"DP_PWR",
            "alternate_pin_names":[],
            "electrical_type":"power_in"
        },
        {
            "reference":"SH",
            "pin_name":"SH",
            "alternate_pin_names":[],
            "electrical_type":"passive"
        },
        {
            "reference":"SH",
            "pin_name":"SH",
            "alternate_pin_names":[],
            "electrical_type":"passive"
        },
        {
            "reference":"SH",
            "pin_name":"SH",
            "alternate_pin_names":[],
            "electrical_type":"passive"
        },
        {
            "reference":"SH",
            "pin_name":"SH",
            "alternate_pin_names":[],
            "electrical_type":"passive"
        }
    ]
}