{
  "id": "linx-technologies-consma001-smd-g",
  "reference": "J",
  "mpn": "CONSMA001-SMD-G",
  "category": "Connector",
  "type": "SMA Connector Receptacle, Female Socket 50Ohm Surface Mount Solder",
  "datasheetUrl": "https://linxtechnologies.com/wp/wp-content/uploads/consma001-smd-g.pdf",
  "assets": {
    "blendfile": false,
    "symbol": false,
    "footprint": false
  },
  "symbolId": "consma001-smd-g",
  "footprintId": "rf-sma-receptical-vertical-consma001-smd-g",
  "blendfileId": "rf-sma-receptical-vertical-consma001-smd-g",
  "manufacturerId": "linx-technologies",
  "tagIds": [
    "connector",
    "receptacle",
    "coaxial"
  ]
}
