{
    "reference":"J",
    "symbol":"PinHeader_2x4_P2.54mm_Drill1.02mm",
    "footprint":"PinHeader_2x4_P2.54mm_Drill1.02mm",
    "datasheet":"https://suddendocs.samtec.com/catalog_english/tsw_th.pdf",
    "manufacturer":"Samtec",
    "mpn":"TSW-104-23-T-D",
    "displayName":null,
    "description":"Header 2.54mm pitch THT 8P in Dual Pin Header",
    "keywords":"PINSTRIP, HEADER, SMT",
    "gitHub":null,
    "blender_model":"PinHeader_2x4_P2.54mm_Drill1.02mm",
    "gltf_model":null,
    "pads":[
        {
            "reference":"1",
            "pin_name":"~",
            "alternate_pin_names":[],
            "electrical_type":"passive"
        },
        {
            "reference":"2",
            "pin_name":"~",
            "alternate_pin_names":[],
            "electrical_type":"passive"
        },
        {
            "reference":"3",
            "pin_name":"~",
            "alternate_pin_names":[],
            "electrical_type":"passive"
        },
        {
            "reference":"4",
            "pin_name":"~",
            "alternate_pin_names":[],
            "electrical_type":"passive"
        },
        {
            "reference":"5",
            "pin_name":"~",
            "alternate_pin_names":[],
            "electrical_type":"passive"
        },
        {
            "reference":"6",
            "pin_name":"~",
            "alternate_pin_names":[],
            "electrical_type":"passive"
        },
        {
            "reference":"7",
            "pin_name":"~",
            "alternate_pin_names":[],
            "electrical_type":"passive"
        },
        {
            "reference":"8",
            "pin_name":"~",
            "alternate_pin_names":[],
            "electrical_type":"passive"
        }
    ]
}