{
    "reference":"Y",
    "symbol":"Resonator_32MHz_ABM12W",
    "footprint":"Resonator_SMD_Abracon_ABM12W_1.6x1.2mm",
    "datasheet":"https://eu.mouser.com/datasheet/2/3/ABM12W-1775148.pdf",
    "manufacturer":"Abracon",
    "mpn":"ABM12W-32.0000MHZ-6-D1X-T3",
    "displayName":null,
    "description":"Crystal, 32 MHz, SMT, 2mm x 1.6mm, 10 ppm, 6 pF, 20 ppm, ABM12W",
    "keywords":"SMT, CERAMIC, OSCILLATOR",
    "gitHub":null,
    "blender_model":"Resonator_SMD_Abracon_ABM12W_1.6x1.2mm",
    "gltf_model":null,
    "pads":[
        {
            "reference":"1",
            "pin_name":"~",
            "alternate_pin_names":[],
            "electrical_type":"passive"
        },
        {
            "reference":"2",
            "pin_name":"SH",
            "alternate_pin_names":[],
            "electrical_type":"passive"
        },
        {
            "reference":"3",
            "pin_name":"~",
            "alternate_pin_names":[],
            "electrical_type":"passive"
        },
        {
            "reference":"4",
            "pin_name":"SH",
            "alternate_pin_names":[],
            "electrical_type":"passive"
        }
    ]
}