{
    "reference":"U",
    "symbol":"TPS613221A_SOT-23-5",
    "footprint":"SOT-23-5",
    "datasheet":"https://www.ti.com/lit/ds/symlink/tps61322.pdf?ts=1679307661323&ref_url=https%253A%252F%252Fwww.ti.com%252Fproduct%252FTPS61322%252Fpart-details%252FTPS613221ADBVT%253Futm_source%253Dgoogle%2526utm_medium%253Dcpc%2526utm_campaign%253Docb-tistore-promo-app_opn_en-cpc-storeic-google-wwe%2526utm_content%253DDevice%2526ds_k%253DTPS613221ADBVT%2526DCM%253Dyes%2526gclid%253DCjwKCAjwiOCgBhAgEiwAjv5whAbq73RvnAdgvLpW8LFuSFEla1kNqoJei2y0mTqS4-Xlc-1KWPDvLxoCIUoQAvD_BwE%2526gclsrc%253Daw.ds",
    "manufacturer":"Texas Instruments",
    "mpn":"TPS613221ADBVT",
    "displayName":null,
    "description":"Synchronous Boost Step Up Regulator, Fixed, 0.9V to 5.5V In, 3.3V/1.2A Out, 1.6MHz, SOT-23-5",
    "keywords":"SMT, PMIC, IC, SWITCHING, VOLTAGE, REGULATOR, DC-DC",
    "gitHub":null,
    "blender_model":"SOT-23-5",
    "gltf_model":"SOT-23-5",
    "pads":[
        {
            "reference":"1",
            "pin_name":"SW",
            "alternate_pin_names":[],
            "electrical_type":"power_in"
        },
        {
            "reference":"2",
            "pin_name":"GND",
            "alternate_pin_names":[],
            "electrical_type":"power_in"
        },
        {
            "reference":"3",
            "pin_name":"NC",
            "alternate_pin_names":[],
            "electrical_type":"no_connect"
        },
        {
            "reference":"4",
            "pin_name":"VOUT",
            "alternate_pin_names":[],
            "electrical_type":"power_in"
        },
        {
            "reference":"5",
            "pin_name":"NC",
            "alternate_pin_names":[],
            "electrical_type":"no_connect"
        }
    ]
}