{
    "id": "panasonic-era2aeb1692x",
    "reference": "R",
    "mpn": "ERA2AEB1692X",
    "category": "Passive",
    "type": "SMD Chip Resistor, 16.9 kohm, \u00b1 0.1%, 62.5 mW, 0402 [1005 Metric], Metal Film (Thin Film)",
    "datasheetUrl": "https://industrial.panasonic.com/cdbs/www-data/pdf/RDM0000/AOA0000C307.pdf",
    "tags": [
        "0402",
        "SMT",
        "RESISTOR",
        "PASSIVE"
    ],
    "assets": {
        "blendfile": true,
        "symbol": true,
        "footprint": true
    },
    "symbolId": "r-16k9-0-1-0402",
    "footprintId": "r-0402-1005metric",
    "blendfileId": "r-0402-1005metric",
    "manufacturerId": "panasonic",
    "tagIds": [
        "0402",
        "smt",
        "resistor",
        "passive"
    ]
}