{
    "reference": "U",
    "symbol": "JS28F320J3D75A",
    "footprint": "TSOP-I-56_18.4x14mm_P0.5mm",
    "datasheet": "https://media-www.micron.com/-/media/client/global/documents/products/data-sheet/nor-flash/parallel/j3/316577_j3d_monolithic_ds.pdf?rev=77975b59947145aab439595289cf09bd",
    "manufacturer": "Micron Technology",
    "mpn": "JS28F320J3D75A",
    "vsd_class": null,
    "description": "FLASH - NOR Memory IC 32Mbit Parallel 75 ns 56-TSOP",
    "keywords": "IC, MEMORY, FLASH, SMT",
    "blender_model": "TSOP-I-56_18.4x14mm_P0.5mm"
}