{
    "id": "bourns-cr1206-fx-5601elf",
    "reference": "R",
    "mpn": "CR1206-FX-5601ELF",
    "category": "Passive",
    "type": "SMT Chip Resistor, Thick Film, AEC-Q200 WCR Series, 5.6 kohm, 200 V, 1206 [3216 Metric], 250 mW",
    "datasheetUrl": null,
    "tags": [
        "1206",
        "SMT",
        "RESISTOR",
        "PASSIVE"
    ],
    "assets": {
        "blendfile": true,
        "symbol": true,
        "footprint": true
    },
    "symbolId": "r-5k6-1206",
    "footprintId": "r-1206-3216metric",
    "blendfileId": "r-1206-3216metric",
    "manufacturerId": "bourns",
    "tagIds": [
        "1206",
        "smt",
        "resistor",
        "passive"
    ]
}