{
    "id": "microchip-technology-mcp1700t-3302e-tt",
    "reference": "U",
    "mpn": "MCP1700T-3302E/TT",
    "category": "IC",
    "type": "Fixed LDO Voltage Regulator, 2.3V to 6V, 178mV Dropout, 3.3Vout, 250mAout, SOT-23-3",
    "datasheetUrl": null,
    "tags": [
        "SMT",
        "REGULATOR",
        "IC",
        "LINEAR"
    ],
    "assets": {
        "blendfile": true,
        "symbol": true,
        "footprint": true
    },
    "symbolId": "mcp1700t-3302e-tt",
    "footprintId": "sot-23-3",
    "blendfileId": "sot-23-3",
    "manufacturerId": "microchip-technology",
    "tagIds": [
        "smt",
        "regulator",
        "ic",
        "linear"
    ]
}