{
    "reference":"U",
    "symbol":"TPS7H4010MRNPTSEP",
    "footprint":"WQFN-30-1EP_6x4mm_P0.5mm",
    "datasheet":"https://www.ti.com/lit/ds/symlink/tps7h4010-sep.pdf",
    "manufacturer":"Texas Instruments",
    "mpn":"TPS7H4010MRNPTSEP",
    "displayName":null,
    "description":"Radiation Hardened Switching Voltage Regulators 3.5V to 36V,5A Synch Step-Down VConverter",
    "keywords":"SMT, PMIC, IC, VOLTAGE",
    "gitHub":null,
    "blender_model":"WQFN-30-1EP_6x4mm_P0.5mm",
    "gltf_model":null,
    "pads":[
        {
            "reference":"1",
            "pin_name":"SW",
            "alternate_pin_names":[],
            "electrical_type":"passive"
        },
        {
            "reference":"2",
            "pin_name":"SW",
            "alternate_pin_names":[],
            "electrical_type":"passive"
        },
        {
            "reference":"3",
            "pin_name":"SW",
            "alternate_pin_names":[],
            "electrical_type":"passive"
        },
        {
            "reference":"4",
            "pin_name":"SW",
            "alternate_pin_names":[],
            "electrical_type":"passive"
        },
        {
            "reference":"5",
            "pin_name":"SW",
            "alternate_pin_names":[],
            "electrical_type":"passive"
        },
        {
            "reference":"6",
            "pin_name":"CBOOT",
            "alternate_pin_names":[],
            "electrical_type":"passive"
        },
        {
            "reference":"7",
            "pin_name":"VCC",
            "alternate_pin_names":[],
            "electrical_type":"power_out"
        },
        {
            "reference":"8",
            "pin_name":"BIAS",
            "alternate_pin_names":[],
            "electrical_type":"passive"
        },
        {
            "reference":"9",
            "pin_name":"RT",
            "alternate_pin_names":[],
            "electrical_type":"passive"
        },
        {
            "reference":"10",
            "pin_name":"SS/TRK",
            "alternate_pin_names":[],
            "electrical_type":"passive"
        },
        {
            "reference":"11",
            "pin_name":"FB",
            "alternate_pin_names":[],
            "electrical_type":"input"
        },
        {
            "reference":"12",
            "pin_name":"NC",
            "alternate_pin_names":[],
            "electrical_type":"passive"
        },
        {
            "reference":"13",
            "pin_name":"NC",
            "alternate_pin_names":[],
            "electrical_type":"passive"
        },
        {
            "reference":"14",
            "pin_name":"NC",
            "alternate_pin_names":[],
            "electrical_type":"passive"
        },
        {
            "reference":"15",
            "pin_name":"NC",
            "alternate_pin_names":[],
            "electrical_type":"passive"
        },
        {
            "reference":"16",
            "pin_name":"PGOOD",
            "alternate_pin_names":[],
            "electrical_type":"output"
        },
        {
            "reference":"17",
            "pin_name":"SYNC/MODE",
            "alternate_pin_names":[],
            "electrical_type":"input"
        },
        {
            "reference":"18",
            "pin_name":"EN",
            "alternate_pin_names":[],
            "electrical_type":"input"
        },
        {
            "reference":"19",
            "pin_name":"GND",
            "alternate_pin_names":[],
            "electrical_type":"passive"
        },
        {
            "reference":"20",
            "pin_name":"PVIN",
            "alternate_pin_names":[],
            "electrical_type":"power_in"
        },
        {
            "reference":"21",
            "pin_name":"PVIN",
            "alternate_pin_names":[],
            "electrical_type":"power_in"
        },
        {
            "reference":"22",
            "pin_name":"PVIN",
            "alternate_pin_names":[],
            "electrical_type":"power_in"
        },
        {
            "reference":"23",
            "pin_name":"GND",
            "alternate_pin_names":[],
            "electrical_type":"passive"
        },
        {
            "reference":"24",
            "pin_name":"GND",
            "alternate_pin_names":[],
            "electrical_type":"passive"
        },
        {
            "reference":"25",
            "pin_name":"GND",
            "alternate_pin_names":[],
            "electrical_type":"passive"
        },
        {
            "reference":"26",
            "pin_name":"GND",
            "alternate_pin_names":[],
            "electrical_type":"passive"
        },
        {
            "reference":"27",
            "pin_name":"NC",
            "alternate_pin_names":[],
            "electrical_type":"passive"
        },
        {
            "reference":"28",
            "pin_name":"NC",
            "alternate_pin_names":[],
            "electrical_type":"passive"
        },
        {
            "reference":"29",
            "pin_name":"NC",
            "alternate_pin_names":[],
            "electrical_type":"passive"
        },
        {
            "reference":"30",
            "pin_name":"NC",
            "alternate_pin_names":[],
            "electrical_type":"passive"
        },
        {
            "reference":"31",
            "pin_name":"GND",
            "alternate_pin_names":[],
            "electrical_type":"passive"
        }
    ]
}